zipstrain/__init__.py
zipstrain/cli.py
zipstrain/compare.py
zipstrain/database.py
zipstrain/profile.py
zipstrain/task_manager.py
zipstrain/utils.py
zipstrain/visualize.py
zipstrain-0.3.1.dist-info/METADATA
zipstrain-0.3.1.dist-info/WHEEL
zipstrain-0.3.1.dist-info/entry_points.txt
zipstrain-0.3.1.dist-info/RECORD
