Metadata-Version: 2.3
Name: zipstrain
Version: 0.3.1
Summary: 
Author: ParsaGhadermazi
Author-email: 54489047+ParsaGhadermazi@users.noreply.github.com
Requires-Python: >=3.12
Classifier: Programming Language :: Python :: 3
Classifier: Programming Language :: Python :: 3.12
Classifier: Programming Language :: Python :: 3.13
Requires-Dist: aiofiles (>=25.1.0,<26.0.0)
Requires-Dist: click (>=8.3.1,<9.0.0)
Requires-Dist: intervaltree (>=3.1.0,<4.0.0)
Requires-Dist: matplotlib (>=3.10.7,<4.0.0)
Requires-Dist: numpy (>=2.3.4,<3.0.0)
Requires-Dist: pandas (>=2.3.3,<3.0.0)
Requires-Dist: plotly (>=6.3.1,<7.0.0)
Requires-Dist: polars (>=1.34.0,<2.0.0)
Requires-Dist: psutil (>=7.1.2,<8.0.0)
Requires-Dist: pyarrow (>=22.0.0,<23.0.0)
Requires-Dist: pydantic (>=2.12.3,<3.0.0)
Requires-Dist: rich (>=14.2.0,<15.0.0)
Requires-Dist: scipy (>=1.16.2,<2.0.0)
Requires-Dist: seaborn (>=0.13.2,<0.14.0)
